[{"map_name":"new_map","map_id":"rFBuAfg0tQ1g","map_description":"","homepage":"https://escher.github.io","schema":"https://escher.github.io/escher/jsonschema/1-0-0#"},{"reactions":{"4":{"name":"","bigg_id":"ADS_reaction","reversibility":false,"label_x":639.31689453125,"label_y":-377.9046325683594,"gene_reaction_rule":"","genes":[],"metabolites":[{"bigg_id":"FPP","coefficient":-1},{"bigg_id":"amorpha","coefficient":1}],"segments":{"16":{"from_node_id":"18","to_node_id":"19","b1":null,"b2":null},"17":{"from_node_id":"20","to_node_id":"19","b1":null,"b2":null},"18":{"from_node_id":"18","to_node_id":"17","b1":{"x":624.31689453125,"y":-449.9046325683594},"b2":{"x":630.3139038085938,"y":-513.150146484375}},"19":{"from_node_id":"20","to_node_id":"21","b1":{"x":624.31689453125,"y":-325.9046325683594},"b2":{"x":624.31689453125,"y":-363.33326721191406}}}},"5":{"name":"","bigg_id":"CYP1AV1CY/PCPR1/CYB5_reaction","reversibility":false,"label_x":679.6889038085938,"label_y":-200.1656379699707,"gene_reaction_rule":"","genes":[],"metabolites":[{"bigg_id":"amorpha","coefficient":-1},{"bigg_id":"artem_alcohol","coefficient":1}],"segments":{"20":{"from_node_id":"22","to_node_id":"23","b1":null,"b2":null},"21":{"from_node_id":"24","to_node_id":"23","b1":null,"b2":null},"22":{"from_node_id":"22","to_node_id":"21","b1":{"x":626.3099365234375,"y":-325.11521911621094},"b2":{"x":624.31689453125,"y":-245.83326721191406}},"23":{"from_node_id":"24","to_node_id":"25","b1":{"x":626.3099365234375,"y":-201.11521911621094},"b2":{"x":626.3099365234375,"y":-146.86521911621094}}}},"6":{"name":"","bigg_id":"ADH1_reaction","reversibility":false,"label_x":639.31689453125,"label_y":68.98259353637695,"gene_reaction_rule":"","genes":[],"metabolites":[{"bigg_id":"artem_alcohol","coefficient":-1},{"bigg_id":"artem_aldehyde","coefficient":1}],"segments":{"24":{"from_node_id":"26","to_node_id":"27","b1":null,"b2":null},"25":{"from_node_id":"28","to_node_id":"27","b1":null,"b2":null},"26":{"from_node_id":"26","to_node_id":"25","b1":{"x":624.31689453125,"y":-3.017406463623047},"b2":{"x":626.3099365234375,"y":-29.365219116210938}},"27":{"from_node_id":"28","to_node_id":"29","b1":{"x":624.31689453125,"y":120.98259353637695},"b2":{"x":626.3098754882812,"y":115.44215393066406}}}},"7":{"name":"","bigg_id":"ALDH1_reaction","reversibility":false,"label_x":641.3098754882812,"label_y":289.4366760253906,"gene_reaction_rule":"","genes":[],"metabolites":[{"bigg_id":"artem_acid_c","coefficient":1},{"bigg_id":"artem_aldehyde","coefficient":-1}],"segments":{"28":{"from_node_id":"30","to_node_id":"31","b1":null,"b2":null},"29":{"from_node_id":"32","to_node_id":"31","b1":null,"b2":null},"30":{"from_node_id":"32","to_node_id":"33","b1":{"x":626.3098754882812,"y":341.4366760253906},"b2":{"x":626.3099365234375,"y":331.9102478027344}},"31":{"from_node_id":"30","to_node_id":"29","b1":{"x":626.3098754882812,"y":217.43667602539062},"b2":{"x":626.3098754882812,"y":232.94215393066406}}}},"12":{"name":"","bigg_id":"Artemisinic_acid_exchange_reaction","reversibility":false,"label_x":643.3029174804688,"label_y":493.9466552734375,"gene_reaction_rule":"","genes":[],"metabolites":[{"bigg_id":"artem_acid_c","coefficient":-1},{"bigg_id":"artem_acid_e","coefficient":1}],"segments":{"45":{"from_node_id":"47","to_node_id":"48","b1":null,"b2":null},"46":{"from_node_id":"49","to_node_id":"48","b1":null,"b2":null},"47":{"from_node_id":"47","to_node_id":"33","b1":{"x":628.3029174804688,"y":421.9466552734375},"b2":{"x":626.3099365234375,"y":449.4102478027344}},"48":{"from_node_id":"49","to_node_id":"50","b1":{"x":628.3029174804688,"y":545.9466552734375},"b2":{"x":626.3098754882812,"y":548.3783264160156}}}},"42":{"name":"Farnesyl diphosphate synthetase (FPP synthetase)","bigg_id":"r868","reversibility":false,"label_x":645.3139038085938,"label_y":-736.900146484375,"gene_reaction_rule":"1091365 or 1126644","genes":[{"name":"125382","bigg_id":"1091365"},{"name":"134931","bigg_id":"1126644"}],"metabolites":[{"bigg_id":"FPP","coefficient":1},{"bigg_id":"GPP","coefficient":-1},{"bigg_id":"IPPP","coefficient":-1},{"bigg_id":"PPI","coefficient":1}],"segments":{"195":{"from_node_id":"197","to_node_id":"198","b1":null,"b2":null},"196":{"from_node_id":"199","to_node_id":"198","b1":null,"b2":null},"197":{"from_node_id":"199","to_node_id":"17","b1":{"x":630.3139038085938,"y":-684.900146484375},"b2":{"x":630.3139038085938,"y":-630.650146484375}},"198":{"from_node_id":"197","to_node_id":"200","b1":{"x":630.3139038085938,"y":-808.900146484375},"b2":{"x":630.3139038085938,"y":-863.150146484375}},"199":{"from_node_id":"197","to_node_id":"201","b1":{"x":630.3139038085938,"y":-812.900146484375},"b2":{"x":634.275146484375,"y":-814.0367431640625}},"200":{"from_node_id":"199","to_node_id":"202","b1":{"x":630.3139038085938,"y":-680.900146484375},"b2":{"x":648.3139038085938,"y":-675.650146484375}}}},"85":{"name":"Prenyltransferase","bigg_id":"r867","reversibility":false,"label_x":645.3139038085938,"label_y":-1086.900146484375,"gene_reaction_rule":"1178523","genes":[{"name":"38877","bigg_id":"1178523"}],"metabolites":[{"bigg_id":"DMPP","coefficient":-1},{"bigg_id":"GPP","coefficient":1},{"bigg_id":"IPPP","coefficient":-1},{"bigg_id":"PPI","coefficient":1}],"segments":{"472":{"from_node_id":"474","to_node_id":"475","b1":null,"b2":null},"473":{"from_node_id":"476","to_node_id":"475","b1":null,"b2":null},"474":{"from_node_id":"474","to_node_id":"477","b1":{"x":630.3139038085938,"y":-1158.900146484375},"b2":{"x":630.3139038085938,"y":-1214.47900390625}},"475":{"from_node_id":"476","to_node_id":"200","b1":{"x":630.3139038085938,"y":-1034.900146484375},"b2":{"x":630.3139038085938,"y":-980.650146484375}}}},"89":{"name":"Isopentenyl diphosphate:dimethylallyl diphosphate isomerase (IPP isomerase)","bigg_id":"r866","reversibility":true,"label_x":405.31390380859375,"label_y":-1311.900146484375,"gene_reaction_rule":"1148497","genes":[{"name":"52621","bigg_id":"1148497"}],"metabolites":[{"bigg_id":"DMPP","coefficient":1},{"bigg_id":"IPPP","coefficient":-1}],"segments":{"496":{"from_node_id":"498","to_node_id":"499","b1":null,"b2":null},"497":{"from_node_id":"500","to_node_id":"499","b1":null,"b2":null},"498":{"from_node_id":"500","to_node_id":"477","b1":{"x":517.3139038085938,"y":-1271.900146484375},"b2":{"x":571.5639038085938,"y":-1273.22900390625}},"499":{"from_node_id":"498","to_node_id":"501","b1":{"x":393.31390380859375,"y":-1271.900146484375},"b2":{"x":339.06390380859375,"y":-1271.900146484375}}}},"90":{"name":"Diphosphomevalonate decarboxylase","bigg_id":"r865","reversibility":false,"label_x":-13.665789297136655,"label_y":-1187.253824564437,"gene_reaction_rule":"1094131","genes":[{"name":"mvd homolog","bigg_id":"1094131"}],"metabolites":[{"bigg_id":"ADP","coefficient":1},{"bigg_id":"ATP","coefficient":-1},{"bigg_id":"CO2","coefficient":1},{"bigg_id":"IPPP","coefficient":1},{"bigg_id":"PI","coefficient":1},{"bigg_id":"PPMVL","coefficient":-1}],"segments":{"500":{"from_node_id":"502","to_node_id":"503","b1":null,"b2":null},"501":{"from_node_id":"504","to_node_id":"503","b1":null,"b2":null},"502":{"from_node_id":"504","to_node_id":"505","b1":{"x":76.7113409010417,"y":-1262.8768280197653},"b2":{"x":94.76416462915796,"y":-1267.942206134137}},"503":{"from_node_id":"502","to_node_id":"506","b1":{"x":75.40043211589028,"y":-1134.8835410154948},"b2":{"x":74.84483210343308,"y":-1080.6363861718899}},"504":{"from_node_id":"504","to_node_id":"507","b1":{"x":76.7113409010417,"y":-1262.8768280197653},"b2":{"x":58.766052659208185,"y":-1268.3108992299603}},"505":{"from_node_id":"504","to_node_id":"501","b1":{"x":76.67037500150619,"y":-1258.8770378008803},"b2":{"x":221.56390380859375,"y":-1271.900146484375}},"506":{"from_node_id":"504","to_node_id":"508","b1":{"x":76.7113409010417,"y":-1262.8768280197653},"b2":{"x":40.61337455097265,"y":-1253.4960324570607}},"507":{"from_node_id":"502","to_node_id":"509","b1":{"x":75.35946621635401,"y":-1130.8837507966134},"b2":{"x":57.306642488238595,"y":-1125.8183726822394}}}},"91":{"name":"Phosphomevalonate kinase","bigg_id":"r864","reversibility":false,"label_x":-94.54414308946747,"label_y":-912.0579200067591,"gene_reaction_rule":"1202754","genes":[{"name":"211137","bigg_id":"1202754"}],"metabolites":[{"bigg_id":"ADP","coefficient":1},{"bigg_id":"ATP","coefficient":-1},{"bigg_id":"PMVL","coefficient":-1},{"bigg_id":"PPMVL","coefficient":1}],"segments":{"508":{"from_node_id":"510","to_node_id":"511","b1":null,"b2":null},"509":{"from_node_id":"512","to_node_id":"511","b1":null,"b2":null},"510":{"from_node_id":"512","to_node_id":"513","b1":{"x":-6.152076444144484,"y":-983.7108306886469},"b2":{"x":-24.097364685979073,"y":-989.1449018988437}},"511":{"from_node_id":"510","to_node_id":"514","b1":{"x":-7.462985229296862,"y":-855.717543684379},"b2":{"x":-8.01858524175367,"y":-801.4703888407728}},"512":{"from_node_id":"510","to_node_id":"515","b1":{"x":-7.503951128832966,"y":-851.7177534654941},"b2":{"x":-27.54183650245676,"y":-846.652375351124}},"513":{"from_node_id":"512","to_node_id":"509","b1":{"x":-6.1930423436808155,"y":-979.7110404697639},"b2":{"x":-5.637442331224236,"y":-1033.9581953133684}}}},"92":{"name":"Mevalonate kinase","bigg_id":"r863","reversibility":false,"label_x":-60.28904542000595,"label_y":-630.9068762889224,"gene_reaction_rule":"1187160","genes":[{"name":"erg12 homolog","bigg_id":"1187160"}],"metabolites":[{"bigg_id":"ADP","coefficient":1},{"bigg_id":"ATP","coefficient":-1},{"bigg_id":"MVL","coefficient":-1},{"bigg_id":"PMVL","coefficient":1}],"segments":{"514":{"from_node_id":"516","to_node_id":"517","b1":null,"b2":null},"515":{"from_node_id":"518","to_node_id":"517","b1":null,"b2":null},"516":{"from_node_id":"518","to_node_id":"519","b1":{"x":-89.01549378933214,"y":-704.5448333575293},"b2":{"x":-106.96078203116645,"y":-709.9789045677262}},"517":{"from_node_id":"516","to_node_id":"520","b1":{"x":-90.32640257448395,"y":-576.5515463532613},"b2":{"x":-90.88200258694098,"y":-522.3043915096547}},"518":{"from_node_id":"516","to_node_id":"521","b1":{"x":-90.36736847401971,"y":-572.5517561343779},"b2":{"x":-108.42019220213632,"y":-567.4863780200052}},"519":{"from_node_id":"518","to_node_id":"515","b1":{"x":-89.05645968886813,"y":-700.5450431386462},"b2":{"x":-90.48592132191914,"y":-754.7921979822522}}}},"93":{"name":"3-hydroxy-3-methylglutaryl-coenzyme A (HMG-CoA) reductase isozyme","bigg_id":"r862","reversibility":true,"label_x":-270.2677848782296,"label_y":-347.6932715359302,"gene_reaction_rule":"1138182 or 1212963 or 1080547 or 1204207","genes":[{"name":"213343","bigg_id":"1138182"},{"name":"hmg1 homolog","bigg_id":"1212963"},{"name":"188317","bigg_id":"1080547"},{"name":"44946","bigg_id":"1204207"}],"metabolites":[{"bigg_id":"COA","coefficient":1},{"bigg_id":"H3MCOA","coefficient":-1},{"bigg_id":"MVL","coefficient":1},{"bigg_id":"NADP","coefficient":2},{"bigg_id":"NADPH","coefficient":-2}],"segments":{"520":{"from_node_id":"522","to_node_id":"523","b1":null,"b2":null},"521":{"from_node_id":"524","to_node_id":"523","b1":null,"b2":null},"522":{"from_node_id":"524","to_node_id":"525","b1":{"x":-171.87891113451877,"y":-425.37883602641307},"b2":{"x":-151.84102576089464,"y":-353.0268862599262}},"523":{"from_node_id":"522","to_node_id":"526","b1":{"x":-173.18981991967144,"y":-297.38554902214355},"b2":{"x":-173.74541993212836,"y":-243.13839417853853}},"524":{"from_node_id":"524","to_node_id":"521","b1":{"x":-171.91987703405545,"y":-421.3790458075298},"b2":{"x":-171.36427702159858,"y":-475.6262006511354}},"525":{"from_node_id":"524","to_node_id":"527","b1":{"x":-171.87891113451877,"y":-425.37883602641307},"b2":{"x":-189.8241993763536,"y":-430.8129072366089}},"526":{"from_node_id":"522","to_node_id":"528","b1":{"x":-173.2307858192067,"y":-293.38575880326164},"b2":{"x":-191.28360954732352,"y":-288.32038068888824}}}},"99":{"name":"Nonaprenyl diphosphate biosynthesis","bigg_id":"r2346","reversibility":false,"label_x":755.3139038085938,"label_y":-961.900146484375,"gene_reaction_rule":"1154946","genes":[{"name":"coq1 homolog","bigg_id":"1154946"}],"metabolites":[{"bigg_id":"GPP","coefficient":-1},{"bigg_id":"IPPP","coefficient":-7},{"bigg_id":"NONAPPP","coefficient":1},{"bigg_id":"PPI","coefficient":7}],"segments":{"560":{"from_node_id":"562","to_node_id":"563","b1":null,"b2":null},"561":{"from_node_id":"564","to_node_id":"563","b1":null,"b2":null},"562":{"from_node_id":"562","to_node_id":"200","b1":{"x":735.3258666992188,"y":-921.900146484375},"b2":{"x":689.0639038085938,"y":-921.900146484375}},"564":{"from_node_id":"564","to_node_id":"566","b1":{"x":867.3139038085938,"y":-921.900146484375},"b2":{"x":921.5639038085938,"y":-921.900146484375}}}},"115":{"name":"Prenyltransferase","bigg_id":"r2005","reversibility":false,"label_x":423.52156303577317,"label_y":-533.5319335550655,"gene_reaction_rule":"1123432","genes":[{"name":"yanG","bigg_id":"1123432"}],"metabolites":[{"bigg_id":"7DEACYANUA","coefficient":1},{"bigg_id":"FPP","coefficient":-1},{"bigg_id":"PPI","coefficient":1},{"bigg_id":"TOLUEK","coefficient":-1}],"segments":{"665":{"from_node_id":"667","to_node_id":"668","b1":null,"b2":null},"666":{"from_node_id":"669","to_node_id":"668","b1":null,"b2":null},"667":{"from_node_id":"669","to_node_id":"670","b1":{"x":521.791379317043,"y":-520.8784547135548},"b2":{"x":473.215633435532,"y":-496.72355020008433}},"668":{"from_node_id":"667","to_node_id":"17","b1":{"x":632.8216556176394,"y":-576.0896650300585},"b2":{"x":577.708833383916,"y":-545.7416093384509}}}},"116":{"name":"Squalene synthase","bigg_id":"r869","reversibility":false,"label_x":740.6595520330034,"label_y":-525.3008753966897,"gene_reaction_rule":"1175565","genes":[{"name":"130900","bigg_id":"1175565"}],"metabolites":[{"bigg_id":"FPP","coefficient":-2},{"bigg_id":"NADP","coefficient":1},{"bigg_id":"NADPH","coefficient":-1},{"bigg_id":"PPI","coefficient":2},{"bigg_id":"SQL","coefficient":1}],"segments":{"671":{"from_node_id":"673","to_node_id":"674","b1":null,"b2":null},"672":{"from_node_id":"675","to_node_id":"674","b1":null,"b2":null},"673":{"from_node_id":"673","to_node_id":"17","b1":{"x":618.6440486198278,"y":-588.4961275311205},"b2":{"x":675.3909386502164,"y":-534.2222560194466}},"677":{"from_node_id":"675","to_node_id":"679","b1":{"x":705.8093515274886,"y":-515.6184574484287},"b2":{"x":780.6671367900688,"y":-508.74264023939946}}}},"117":{"name":"tyrosine O-prenyltransferase","bigg_id":"r3000","reversibility":false,"label_x":747.3302063298784,"label_y":-1204.02157852169,"gene_reaction_rule":"1162228","genes":[{"name":"TyrPT","bigg_id":"1162228"}],"metabolites":[{"bigg_id":"4ODMLTYR","coefficient":1},{"bigg_id":"DMPP","coefficient":-1},{"bigg_id":"PPI","coefficient":1},{"bigg_id":"TYR","coefficient":-1}],"segments":{"678":{"from_node_id":"680","to_node_id":"681","b1":null,"b2":null},"679":{"from_node_id":"682","to_node_id":"681","b1":null,"b2":null},"680":{"from_node_id":"682","to_node_id":"683","b1":{"x":767.0041757462386,"y":-1161.0751224874912},"b2":{"x":767.4601055400688,"y":-1164.79552720229}},"681":{"from_node_id":"680","to_node_id":"477","b1":{"x":671.862859654984,"y":-1240.599521085808},"b2":{"x":675.3909386502164,"y":-1235.5511134413216}}}},"118":{"name":"tyrosine O-prenyltransferase","bigg_id":"r3001","reversibility":false,"label_x":769.9220581054688,"label_y":-1299.9488525390625,"gene_reaction_rule":"1162228","genes":[{"name":"TyrPT","bigg_id":"1162228"}],"metabolites":[{"bigg_id":"4ODMDTYR","coefficient":1},{"bigg_id":"DMPP","coefficient":-1},{"bigg_id":"DTYR","coefficient":-1},{"bigg_id":"PPI","coefficient":1}],"segments":{"684":{"from_node_id":"686","to_node_id":"687","b1":null,"b2":null},"685":{"from_node_id":"688","to_node_id":"687","b1":null,"b2":null},"686":{"from_node_id":"688","to_node_id":"689","b1":{"x":867.3139038085938,"y":-1273.22900390625},"b2":{"x":917.5798950195312,"y":-1271.9010009765625}},"687":{"from_node_id":"686","to_node_id":"477","b1":{"x":743.3139038085938,"y":-1273.22900390625},"b2":{"x":689.0639038085938,"y":-1273.22900390625}}}},"120":{"name":"tyrosine O-prenyltransferase","bigg_id":"r3006","reversibility":false,"label_x":787.1861572265625,"label_y":-1386.2696533203125,"gene_reaction_rule":"1162228","genes":[{"name":"TyrPT","bigg_id":"1162228"}],"metabolites":[{"bigg_id":"4O3OLTYR","coefficient":1},{"bigg_id":"DMPP","coefficient":-1},{"bigg_id":"LDOPA","coefficient":-1},{"bigg_id":"PPI","coefficient":1}],"segments":{"696":{"from_node_id":"698","to_node_id":"699","b1":null,"b2":null},"697":{"from_node_id":"700","to_node_id":"699","b1":null,"b2":null},"698":{"from_node_id":"700","to_node_id":"701","b1":{"x":895.2021484375,"y":-1359.5498046875},"b2":{"x":924.2199096679688,"y":-1360.8778076171875}},"699":{"from_node_id":"698","to_node_id":"477","b1":{"x":731.36181640625,"y":-1358.2218017578125},"b2":{"x":689.0639038085938,"y":-1273.22900390625}}}},"122":{"name":"tyrosine O-prenyltransferase","bigg_id":"r3008","reversibility":false,"label_x":649.4864799539537,"label_y":-1410.9044451977447,"gene_reaction_rule":"1162228","genes":[{"name":"TyrPT","bigg_id":"1162228"}],"metabolites":[{"bigg_id":"7DMLTRP","coefficient":1},{"bigg_id":"DMPP","coefficient":-1},{"bigg_id":"PPI","coefficient":1},{"bigg_id":"TRP","coefficient":-1}],"segments":{"708":{"from_node_id":"710","to_node_id":"711","b1":null,"b2":null},"709":{"from_node_id":"712","to_node_id":"711","b1":null,"b2":null},"710":{"from_node_id":"712","to_node_id":"713","b1":{"x":797.1380667111091,"y":-1441.5700228881815},"b2":{"x":802.1242929462776,"y":-1448.2314648897811}},"711":{"from_node_id":"710","to_node_id":"477","b1":{"x":709.8545384414386,"y":-1353.492865277382},"b2":{"x":671.6679948234578,"y":-1314.959108822657}}}},"126":{"name":"Mevalonate oxidase","bigg_id":"r2607","reversibility":false,"label_x":-324.7304542464671,"label_y":-674.3714457864431,"gene_reaction_rule":"","genes":[],"metabolites":[{"bigg_id":"H2O","coefficient":1},{"bigg_id":"MEVAL","coefficient":1},{"bigg_id":"MVL","coefficient":-1},{"bigg_id":"O2","coefficient":-1}],"segments":{"734":{"from_node_id":"736","to_node_id":"737","b1":null,"b2":null},"735":{"from_node_id":"738","to_node_id":"737","b1":null,"b2":null},"736":{"from_node_id":"738","to_node_id":"739","b1":{"x":-388.60994994511344,"y":-627.9277743839477},"b2":{"x":-385.65737584356305,"y":-666.1170506768264}},"737":{"from_node_id":"738","to_node_id":"740","b1":{"x":-384.99422613477407,"y":-627.9277743839477},"b2":{"x":-434.03248031250246,"y":-627.9277743839477}},"738":{"from_node_id":"736","to_node_id":"521","b1":{"x":-272.9067880142519,"y":-609.965280644499},"b2":{"x":-223.8685338365235,"y":-559.4992268050951}},"739":{"from_node_id":"736","to_node_id":"741","b1":{"x":-269.29106420391247,"y":-627.9277743839477},"b2":{"x":-256.8472151002211,"y":-622.2800123841239}}}},"132":{"name":"3-hydroxy-3-methylglutaryl coenzyme A synthase","bigg_id":"r861","reversibility":true,"label_x":-159.34710658156246,"label_y":0.608524661311094,"gene_reaction_rule":"1106564 or 1134930","genes":[{"name":"55566","bigg_id":"1106564"},{"name":"56215","bigg_id":"1134930"}],"metabolites":[{"bigg_id":"AACCOA","coefficient":-1},{"bigg_id":"ACCOA","coefficient":-1},{"bigg_id":"COA","coefficient":1},{"bigg_id":"H2O","coefficient":-1},{"bigg_id":"H3MCOA","coefficient":1}],"segments":{"764":{"from_node_id":"766","to_node_id":"767","b1":null,"b2":null},"765":{"from_node_id":"768","to_node_id":"767","b1":null,"b2":null},"766":{"from_node_id":"766","to_node_id":"769","b1":{"x":-174.34710658156243,"y":52.608524661311094},"b2":{"x":-96.96847498976558,"y":26.503788333186094}},"767":{"from_node_id":"766","to_node_id":"770","b1":{"x":-174.34710658156243,"y":56.608524661311094},"b2":{"x":-195.0364223774609,"y":118.40445361638922}},"768":{"from_node_id":"768","to_node_id":"771","b1":{"x":-174.34710658156246,"y":-75.3914753386889},"b2":{"x":-192.34710658156246,"y":-80.6414753386889}},"769":{"from_node_id":"766","to_node_id":"772","b1":{"x":-174.34710658156243,"y":56.608524661311094},"b2":{"x":-192.34710658156246,"y":61.858524661311094}},"770":{"from_node_id":"768","to_node_id":"526","b1":{"x":-174.34710658156246,"y":-71.3914753386889},"b2":{"x":-174.34710658156246,"y":-125.6414753386889}}}}},"nodes":{"17":{"node_type":"metabolite","x":630.3139038085938,"y":-571.900146484375,"bigg_id":"FPP","name":"trans,trans-Farnesyl diphosphate","label_x":664.3094177246094,"label_y":-595.8881530761719,"node_is_primary":true},"18":{"node_type":"multimarker","x":624.31689453125,"y":-407.9046325683594},"19":{"node_type":"midmarker","x":624.31689453125,"y":-387.9046325683594},"20":{"node_type":"multimarker","x":624.31689453125,"y":-367.9046325683594},"21":{"node_type":"metabolite","x":624.31689453125,"y":-304.58326721191406,"bigg_id":"amorpha","name":"Amorphadiene","label_x":649.31689453125,"label_y":-304.58326721191406,"node_is_primary":true},"22":{"node_type":"multimarker","x":626.3099365234375,"y":-283.11521911621094},"23":{"node_type":"midmarker","x":626.3099365234375,"y":-263.11521911621094},"24":{"node_type":"multimarker","x":626.3099365234375,"y":-243.11521911621094},"25":{"node_type":"metabolite","x":626.3099365234375,"y":-88.11521911621094,"bigg_id":"artem_alcohol","name":"Artemisinic alcohol","label_x":651.3099365234375,"label_y":-88.11521911621094,"node_is_primary":true},"26":{"node_type":"multimarker","x":624.31689453125,"y":38.98259353637695},"27":{"node_type":"midmarker","x":624.31689453125,"y":58.98259353637695},"28":{"node_type":"multimarker","x":624.31689453125,"y":78.98259353637695},"29":{"node_type":"metabolite","x":626.3098754882812,"y":174.19215393066406,"bigg_id":"artem_aldehyde","name":"Artemisinic aldehyde","label_x":651.3098754882812,"label_y":174.19215393066406,"node_is_primary":true},"30":{"node_type":"multimarker","x":626.3098754882812,"y":259.4366760253906},"31":{"node_type":"midmarker","x":626.3098754882812,"y":279.4366760253906},"32":{"node_type":"multimarker","x":626.3098754882812,"y":299.4366760253906},"33":{"node_type":"metabolite","x":626.3099365234375,"y":390.6602478027344,"bigg_id":"artem_acid_c","name":"Artemisinic acid_c","label_x":651.3099365234375,"label_y":390.6602478027344,"node_is_primary":true},"47":{"node_type":"multimarker","x":628.3029174804688,"y":463.9466552734375},"48":{"node_type":"midmarker","x":628.3029174804688,"y":483.9466552734375},"49":{"node_type":"multimarker","x":628.3029174804688,"y":503.9466552734375},"50":{"node_type":"metabolite","x":626.3098754882812,"y":607.1283264160156,"bigg_id":"artem_acid_e","name":"Artemisinic acid_e","label_x":651.3098754882812,"label_y":607.1283264160156,"node_is_primary":true},"197":{"node_type":"multimarker","x":630.3139038085938,"y":-766.900146484375},"198":{"node_type":"midmarker","x":630.3139038085938,"y":-746.900146484375},"199":{"node_type":"multimarker","x":630.3139038085938,"y":-726.900146484375},"200":{"node_type":"metabolite","x":630.3139038085938,"y":-921.900146484375,"bigg_id":"GPP","name":"Geranyl diphosphate","label_x":551.4697265625,"label_y":-935.879150390625,"node_is_primary":true},"201":{"node_type":"metabolite","x":696.275146484375,"y":-847.7867431640625,"bigg_id":"IPPP","name":"Isopentenyl diphosphate","label_x":711.275146484375,"label_y":-847.7867431640625,"node_is_primary":false},"202":{"node_type":"metabolite","x":710.3139038085938,"y":-641.900146484375,"bigg_id":"PPI","name":"Pyrophosphate","label_x":725.3139038085938,"label_y":-641.900146484375,"node_is_primary":false},"474":{"node_type":"multimarker","x":630.3139038085938,"y":-1116.900146484375},"475":{"node_type":"midmarker","x":630.3139038085938,"y":-1096.900146484375},"476":{"node_type":"multimarker","x":630.3139038085938,"y":-1076.900146484375},"477":{"node_type":"metabolite","x":630.3139038085938,"y":-1273.22900390625,"bigg_id":"DMPP","name":"Dimethylallyl diphosphate","label_x":555.7130126953125,"label_y":-1232.0606689453125,"node_is_primary":true},"498":{"node_type":"multimarker","x":435.31390380859375,"y":-1271.900146484375},"499":{"node_type":"midmarker","x":455.31390380859375,"y":-1271.900146484375},"500":{"node_type":"multimarker","x":475.31390380859375,"y":-1271.900146484375},"501":{"node_type":"metabolite","x":280.31390380859375,"y":-1271.900146484375,"bigg_id":"IPPP","name":"Isopentenyl diphosphate","label_x":258.7139038085937,"label_y":-1231.900146484375,"node_is_primary":true},"502":{"node_type":"multimarker","x":75.83057406101801,"y":-1176.8813383137704},"503":{"node_type":"midmarker","x":76.03540355869842,"y":-1196.8802894081873},"504":{"node_type":"multimarker","x":76.24023305637766,"y":-1216.8792405026052},"505":{"node_type":"metabolite","x":157.10656279918584,"y":-1301.0554646631572,"bigg_id":"ADP","name":"ADP","label_x":108.08751677867798,"label_y":-1323.7100056787822,"node_is_primary":false},"506":{"node_type":"metabolite","x":74.24314545399889,"y":-1021.8894673320397,"bigg_id":"ATP","name":"ATP","label_x":58.04314545399896,"label_y":-981.8894673320397,"node_is_primary":false},"507":{"node_type":"metabolite","x":-2.885045956150236,"y":-1302.6941006445986,"bigg_id":"CO2","name":"Carbon dioxide","label_x":-19.08504595615028,"label_y":-1322.6941006445986,"node_is_primary":false},"508":{"node_type":"metabolite","x":-83.08567983149777,"y":-1283.5144675408987,"bigg_id":"PI","name":"Orthophosphate","label_x":-93.88567983149784,"label_y":-1303.5144675408987,"node_is_primary":false},"509":{"node_type":"metabolite","x":-5.035755681789283,"y":-1092.705114153218,"bigg_id":"PPMVL","name":"(R)-5-Diphosphomevalonate","label_x":-51.88635306338108,"label_y":-1134.540807512593,"node_is_primary":true},"510":{"node_type":"multimarker","x":-7.032843284169132,"y":-897.7153409826537},"511":{"node_type":"midmarker","x":-6.8280137864889525,"y":-917.7142920770716},"512":{"node_type":"multimarker","x":-6.6231842888088295,"y":-937.7132431714874},"513":{"node_type":"metabolite","x":-85.74846330133693,"y":-1023.5281033134804,"bigg_id":"ADP","name":"ADP","label_x":-101.94846330133697,"label_y":-1043.5281033134804,"node_is_primary":false},"514":{"node_type":"metabolite","x":-8.620271891188452,"y":-742.7234700009221,"bigg_id":"ATP","name":"ATP","label_x":-24.82027189118844,"label_y":-702.7234700009221,"node_is_primary":false},"515":{"node_type":"metabolite","x":-89.88423467248492,"y":-813.5391168221036,"bigg_id":"PMVL","name":"(R)-5-Phosphomevalonate","label_x":-125.37965093225057,"label_y":-849.419609986166,"node_is_primary":true},"516":{"node_type":"multimarker","x":-89.89626062935616,"y":-618.5493436515371},"517":{"node_type":"midmarker","x":-89.69143113167587,"y":-638.5482947459539},"518":{"node_type":"multimarker","x":-89.48660163399632,"y":-658.5472458403717},"519":{"node_type":"metabolite","x":-168.61188064652447,"y":-744.3621059823622,"bigg_id":"ADP","name":"ADP","label_x":-184.81188064652451,"label_y":-764.3621059823622,"node_is_primary":false},"520":{"node_type":"metabolite","x":-91.48368923637588,"y":-463.55747266980575,"bigg_id":"ATP","name":"ATP","label_x":-107.68368923637593,"label_y":-423.55747266980575,"node_is_primary":false},"521":{"node_type":"metabolite","x":-170.76259037216323,"y":-534.3731194909851,"bigg_id":"MVL","name":"(R)-Mevalonate","label_x":-194.90283695419453,"label_y":-574.2237054284851,"node_is_primary":true},"522":{"node_type":"multimarker","x":-172.75967797454297,"y":-339.3833463204189},"523":{"node_type":"midmarker","x":-172.55484847686284,"y":-359.38229741483633},"524":{"node_type":"multimarker","x":-172.3500189791838,"y":-379.3812485092535},"525":{"node_type":"metabolite","x":-89.49862759086807,"y":-386.1401447889464,"bigg_id":"COA","name":"Coenzyme A","label_x":-89.81814587089741,"label_y":-356.0654377576964,"node_is_primary":false},"526":{"node_type":"metabolite","x":-174.34710658156246,"y":-184.3914753386889,"bigg_id":"H3MCOA","name":"(S)-3-Hydroxy-3-methylglutaryl-CoA","label_x":-135.3206692036331,"label_y":-171.1763874480639,"node_is_primary":true},"527":{"node_type":"metabolite","x":-251.4752979917116,"y":-465.1961086512447,"bigg_id":"NADP","name":"NADP+","label_x":-273.0752979917115,"label_y":-485.1961086512447,"node_is_primary":false},"528":{"node_type":"metabolite","x":-253.62600771735015,"y":-255.20712215986737,"bigg_id":"NADPH","name":"NADPH","label_x":-346.13296572516276,"label_y":-263.2967522868205,"node_is_primary":false},"562":{"node_type":"multimarker","x":777.3258666992188,"y":-921.900146484375},"563":{"node_type":"midmarker","x":805.3139038085938,"y":-921.900146484375},"564":{"node_type":"multimarker","x":825.3139038085938,"y":-921.900146484375},"566":{"node_type":"metabolite","x":980.3139038085938,"y":-921.900146484375,"bigg_id":"NONAPPP","name":"all-trans-nonaprenyl diphosphate","label_x":942.5139038085938,"label_y":-881.900146484375,"node_is_primary":true},"667":{"node_type":"multimarker","x":595.2146265480826,"y":-557.3890937938233},"668":{"node_type":"midmarker","x":577.3065174673412,"y":-548.4840598718067},"669":{"node_type":"multimarker","x":559.3984083865998,"y":-539.5790259497899},"670":{"node_type":"metabolite","x":420.6105630108543,"y":-470.5650130541602,"bigg_id":"7DEACYANUA","name":"7-deacetoxyyanuthone A","label_x":403.4556054573966,"label_y":-415.09796364171586,"node_is_primary":true},"673":{"node_type":"multimarker","x":650.8693331023495,"y":-561.5604441349165},"674":{"node_type":"midmarker","x":666.2147066654551,"y":-548.7339282319622},"675":{"node_type":"multimarker","x":673.5840670449669,"y":-542.5541408446328},"679":{"node_type":"metabolite","x":825.7441716316914,"y":-471.0647497744711,"bigg_id":"SQL","name":"Squalene","label_x":817.5104597552483,"label_y":-514.7933180329487,"node_is_primary":true},"680":{"node_type":"multimarker","x":704.0881441375058,"y":-1213.663837689604},"681":{"node_type":"midmarker","x":719.4335177006113,"y":-1200.8373217866497},"682":{"node_type":"multimarker","x":734.7788912637169,"y":-1188.0108058836952},"683":{"node_type":"metabolite","x":812.5371403816914,"y":-1127.1176367373616,"bigg_id":"4ODMLTYR","name":"4-O-dimethylallyl-L-tyrosine","label_x":804.3034285052483,"label_y":-1170.8462049958393,"node_is_primary":true},"686":{"node_type":"multimarker","x":785.3139038085938,"y":-1273.22900390625},"687":{"node_type":"midmarker","x":805.3139038085938,"y":-1273.22900390625},"688":{"node_type":"multimarker","x":825.3139038085938,"y":-1273.22900390625},"689":{"node_type":"metabolite","x":976.3298950195312,"y":-1271.9010009765625,"bigg_id":"4ODMDTYR","name":"4-O-dimethylallyl-D-tyrosine","label_x":933.1298950195312,"label_y":-1231.9010009765625,"node_is_primary":true},"698":{"node_type":"multimarker","x":773.36181640625,"y":-1358.2218017578125},"699":{"node_type":"midmarker","x":809.2979125976562,"y":-1360.8778076171875},"700":{"node_type":"multimarker","x":853.2021484375,"y":-1359.5498046875},"701":{"node_type":"metabolite","x":982.9699096679688,"y":-1360.8778076171875,"bigg_id":"4O3OLTYR","name":"(2S)-2-amino-3-{3-hydroxy-4-[(3-methylbut-2-en-1-yl)oxy]phenyl}propanoic acid","label_x":939.7699096679687,"label_y":-1320.8778076171875,"node_is_primary":true},"710":{"node_type":"multimarker","x":739.4183141456818,"y":-1383.3254509197495},"711":{"node_type":"midmarker","x":753.4963025762739,"y":-1397.5314440827817},"712":{"node_type":"multimarker","x":767.5742910068659,"y":-1411.737437245814},"713":{"node_type":"metabolite","x":843.4783839611416,"y":-1489.9615698061882,"bigg_id":"7DMLTRP","name":"7-(3-methylbut-2-enyl)-L-tryptophan","label_x":860.6409224257011,"label_y":-1442.9777593977137,"node_is_primary":true},"736":{"node_type":"multimarker","x":-310.8718880228158,"y":-627.9277743839477},"737":{"node_type":"midmarker","x":-328.950507074513,"y":-627.9277743839477},"738":{"node_type":"multimarker","x":-347.0291261262101,"y":-627.9277743839477},"739":{"node_type":"metabolite","x":-389.64898330649646,"y":-736.5949164920017,"bigg_id":"H2O","name":"Water","label_x":-374.64898330649646,"label_y":-736.5949164920017,"node_is_primary":false},"740":{"node_type":"metabolite","x":-487.13842377686274,"y":-627.9277743839477,"bigg_id":"MEVAL","name":"Mevalon","label_x":-505.0356140427592,"label_y":-684.3714457864431,"node_is_primary":true},"741":{"node_type":"metabolite","x":-199.8234832636768,"y":-663.8895846894708,"bigg_id":"O2","name":"Oxygen","label_x":-184.8234832636768,"label_y":-663.8895846894708,"node_is_primary":false},"766":{"node_type":"multimarker","x":-174.34710658156246,"y":10.608524661311094},"767":{"node_type":"midmarker","x":-174.34710658156246,"y":-9.391475338688906},"768":{"node_type":"multimarker","x":-174.34710658156246,"y":-29.391475338688906},"769":{"node_type":"metabolite","x":-96.96847498976558,"y":85.2537883331861,"bigg_id":"AACCOA","name":"Acetoacetyl coenzyme A","label_x":-71.96847498976558,"label_y":85.2537883331861,"node_is_primary":false},"770":{"node_type":"metabolite","x":-133.0364223774609,"y":152.15445361638922,"bigg_id":"ACCOA","name":"Acetyl coenzyme A","label_x":-85.29931033217281,"label_y":170.01105914617438,"node_is_primary":true},"771":{"node_type":"metabolite","x":-254.34710658156246,"y":-114.3914753386889,"bigg_id":"COA","name":"Coenzyme A","label_x":-281.34710658156246,"label_y":-84.3914753386889,"node_is_primary":false},"772":{"node_type":"metabolite","x":-254.34710658156246,"y":95.6085246613111,"bigg_id":"H2O","name":"Water","label_x":-281.34710658156246,"label_y":125.6085246613111,"node_is_primary":false}},"text_labels":{"2":{"x":-393.71016693115234,"y":287.4543151855469,"text":"Carbon metabolism"},"3":{"x":-1099.046142578125,"y":-619.2645263671875,"text":"Secondary Metabolites"},"5":{"x":1141.9581298828125,"y":-1274.9990234375,"text":"Biosynthesis of terpenoids"},"7":{"x":901.8858642578125,"y":-457.5631103515625,"text":"Sterol biosynthesis"}},"canvas":{"x":-1536,"y":-1693.1142578125,"width":4608,"height":3136.3143310546875}}]